README.md
cobra_py/__init__.py
cobra_py/graphics_client.py
cobra_py/graphics_server.py
cobra_py/kbd_layout.py
cobra_py/keysyms.py
cobra_py/prompt_utils.py
cobra_py/repl.py
cobra_py/resources/fonts/monoid.ttf
cobra_py/resources/fonts/monoid_license.md
cobra_py/rl.py
cobra_py/terminal.py
examples/raygui_checkboxes.py
examples/raylib_fonts.py
examples/raylib_hello.py
examples/raylib_terminal.py
examples/shader.py
include/_raylib.h
include/gui_textbox_extended.h
include/raygui.h
include/ricons.h
raylib.patch
tasks.py
cobra_py-0.0.3.dist-info/entry_points.txt
cobra_py-0.0.3.dist-info/WHEEL
cobra_py-0.0.3.dist-info/METADATA
cobra_py-0.0.3.dist-info/RECORD
