Metadata-Version: 2.1
Name: cobra-py
Version: 0.0.3
Summary: An 80s style Python runtime and development environment
License: MIT
Author: Roberto Alsina
Author-email: roberto.alsina@gmail.com
Requires-Python: >=3.8,<4.0
Classifier: License :: OSI Approved :: MIT License
Classifier: Programming Language :: Python :: 3
Classifier: Programming Language :: Python :: 3.8
Requires-Dist: ipcqueue (>=0.9.6,<0.10.0)
Requires-Dist: jedi (>=0.17.2,<0.18.0)
Requires-Dist: prompt_toolkit (>=3.0.7,<4.0.0)
Requires-Dist: pygments (>=2.7.1,<3.0.0)
Requires-Dist: pyte (>=0.8.0,<0.9.0)
